MANIFEST.in
README.rst
setup.py
delegate/__init__.py
minidelegate.egg-info/PKG-INFO
minidelegate.egg-info/SOURCES.txt
minidelegate.egg-info/dependency_links.txt
minidelegate.egg-info/not-zip-safe
minidelegate.egg-info/top_level.txt